topsis/__init__.py
topsis/topsis.py
topsis_102203511-1.0.0.dist-info/LICENSE
topsis_102203511-1.0.0.dist-info/METADATA
topsis_102203511-1.0.0.dist-info/WHEEL
topsis_102203511-1.0.0.dist-info/top_level.txt
topsis_102203511-1.0.0.dist-info/RECORD
